byrdocs/__init__.py
byrdocs/custom_prompt.py
byrdocs/history_manager.py
byrdocs/main_menu.py
byrdocs/resources.py
byrdocs/yaml_init.py
byrdocs_cli-0.5.8.dist-info/licenses/LICENSE
byrdocs_cli-0.5.8.dist-info/METADATA
byrdocs_cli-0.5.8.dist-info/WHEEL
byrdocs_cli-0.5.8.dist-info/entry_points.txt
byrdocs_cli-0.5.8.dist-info/top_level.txt
byrdocs_cli-0.5.8.dist-info/RECORD
