Metadata-Version: 2.4
Name: byrdocs_cli
Version: 0.5.8
Summary: A simple command line tool for BYR Docs
Home-page: https://github.com/byrdocs/byrdocs-cli
Author: Rikka
Author-email: Rikka <rikka@byrdocs.org>
License: MIT License
Project-URL: Homepage, https://github.com/byrdocs/byrdocs-cli
Classifier: Programming Language :: Python :: 3
Classifier: License :: OSI Approved :: MIT License
Classifier: Operating System :: OS Independent
Requires-Python: >=3.8
License-File: LICENSE
Requires-Dist: requests>=2.25.1
Requires-Dist: boto3==1.35.62
Requires-Dist: botocore==1.35.62
Requires-Dist: argcomplete==3.5.1
Requires-Dist: tqdm==4.67.0
Requires-Dist: InquirerPy==0.3.4
Requires-Dist: pyyaml==6.0.2
Requires-Dist: isbnlib==3.10.14
Requires-Dist: pinyin==0.4.0
Requires-Dist: yaspin==3.1.0
Dynamic: license-file
